shlep-3.2.0.dist-info/METADATA
shlep-3.2.0.dist-info/WHEEL
shlep-3.2.0.dist-info/entry_points.txt
shlep-3.2.0.dist-info/licenses/LICENSE
shlep/__init__.py
shlep/main.py
shlep-3.2.0.dist-info/RECORD
