Metadata-Version: 2.1
Name: shlep
Version: 3.2.0
Summary: gather directory contents into a single file
Author-Email: Stephan Fitzpatrick <knowsuchagency@gmail.com>
License: Apache-2.0
Requires-Python: >=3.10
Requires-Dist: pathspec>=0.11.1
